{
  "WORKLIST": [
    {
      "MARK": "",
      "SKOSTL": "",
      "LSTAR": "",
      "SEBELN": "",
      "SEBELP": "00000",
      "SPRZNR": "",
      "LSTNR": "",
      "RKOSTL": "",
      "RPROJ": "00000000",
      "RAUFNR": "000505220105",
      "RNPLNR": "",
      "RAUFPL": "0000000000",
      "RAPLZL": "00000000",
      "RKDAUF": "",
      "RKDPOS": "000000",
      "RKSTR": "",
      "RPRZNR": "",
      "PAOBJNR": "0000000000",
      "FUND": "",
      "FUNC_AREA": "",
      "GRANT_NBR": "",
      "S_FUND": "",
      "S_FUNC_AREA": "",
      "S_GRANT_NBR": "",
      "BUDGET_PD": "",
      "SBUDGET_PD": "",
      "SUMDAYW": 0.0,
      "DAY1": 0.0,
      "DAY2": 0.0,
      "DAY3": 0.0,
      "DAY4": 0.0,
      "DAY5": 0.0,
      "DAY6": 0.0,
      "DAY7": 0.0,
      "DAY8": 0.0,
      "DAY9": 0.0,
      "DAY10": 0.0,
      "DAY11": 0.0,
      "DAY12": 0.0,
      "DAY13": 0.0,
      "DAY14": 0.0,
      "DAY15": 0.0,
      "DAY16": 0.0,
      "DAY17": 0.0,
      "DAY18": 0.0,
      "DAY19": 0.0,
      "DAY20": 0.0,
      "DAY21": 0.0,
      "DAY22": 0.0,
      "DAY23": 0.0,
      "DAY24": 0.0,
      "DAY25": 0.0,
      "DAY26": 0.0,
      "DAY27": 0.0,
      "DAY28": 0.0,
      "DAY29": 0.0,
      "DAY30": 0.0,
      "DAY31": 0.0,
      "VORNR": "",
      "UVORN": "",
      "BEDID": "000000000000",
      "KAPAR": "",
      "ARBPL": "",
      "POSID": "",
      "ZZ_PSPTXT": "",
      "ZZ_NPKTXT": "",
      "ZZ_NPVTXT": "",
      "ZZCONTPERS": "",
      "ZZSUBTYPE": "",
      "ZZOBJNR": "",
      "ZZBUKRS": "",
      "ZZ_PROJN": "00000000",
      "ZZRESET_APPR": "00",
      "ZZ_INTERNAL_MEMO": "",
      "ZCPR_GUID": "00145E5A9BCA1EE292EF50A4BC02D021",
      "ZCPR_EXTID": "I2M_2013_RESEARCH_INNOV",
      "ZCPR_OBJGUID": "00145E5A9BCA1EE292EFC980E8D2B021",
      "ZCPR_OBJGEXTID": "00000000000000617094",
      "ZCPR_OBJTYPE": "TTO",
      "ZZCATSSHORTT": "",
      "ZZEXP_FLAT_RATE": "",
      "ZZMOB_ERR_FLAG": "",
      "ZZBYD": "",
      "ZZ_LOCATION": "",
      "ZZSTATUS": "00",
      "ZZGUID_ITEM": "",
      "ZZPRCTR": "",
      "ZZKOSTV": "",
      "ZZ_REL_OBJ": "",
      "ARBID": "00000000",
      "WERKS": "",
      "SPLIT": "000",
      "LTXA1": "",
      "FSTAD": "0000-00-00",
      "SSTAD": "0000-00-00",
      "FENDD": "0000-00-00",
      "SENDD": "0000-00-00",
      "KBEAREST": 0,
      "VERTL": "",
      "AUTYP": "00",
      "KALID": "",
      "RPROJ_EXT": "",
      "DISPTEXTW1": "I2M_2013_RESEARCH_INNOV",
      "DISPTEXTW2": "I2M Research & Innovation",
      "KPER_SINGLE": "",
      "KPER_COLLECT": "",
      "CPR_GUID": "",
      "CPR_EXTID": "",
      "CPR_OBJGUID": "",
      "CPR_OBJGEXTID": "",
      "CPR_OBJTYPE": "",
      "CPR_TEXT": "",
      "CPR_OBJTEXT": "",
      "PERASCE": "00000000",
      "PRTXTCE": "",
      "TASKTYPE": "",
      "TASKLEVEL": "",
      "TASKCOMPONENT": ""
    },
    {
      "MARK": "",
      "SKOSTL": "",
      "LSTAR": "",
      "SEBELN": "",
      "SEBELP": "00000",
      "SPRZNR": "",
      "LSTNR": "",
      "RKOSTL": "",
      "RPROJ": "00000000",
      "RAUFNR": "000505220192",
      "RNPLNR": "",
      "RAUFPL": "0000000000",
      "RAPLZL": "00000000",
      "RKDAUF": "",
      "RKDPOS": "000000",
      "RKSTR": "",
      "RPRZNR": "",
      "PAOBJNR": "0000000000",
      "FUND": "",
      "FUNC_AREA": "",
      "GRANT_NBR": "",
      "S_FUND": "",
      "S_FUNC_AREA": "",
      "S_GRANT_NBR": "",
      "BUDGET_PD": "",
      "SBUDGET_PD": "",
      "SUMDAYW": 0.0,
      "DAY1": 0.0,
      "DAY2": 0.0,
      "DAY3": 0.0,
      "DAY4": 0.0,
      "DAY5": 0.0,
      "DAY6": 0.0,
      "DAY7": 0.0,
      "DAY8": 0.0,
      "DAY9": 0.0,
      "DAY10": 0.0,
      "DAY11": 0.0,
      "DAY12": 0.0,
      "DAY13": 0.0,
      "DAY14": 0.0,
      "DAY15": 0.0,
      "DAY16": 0.0,
      "DAY17": 0.0,
      "DAY18": 0.0,
      "DAY19": 0.0,
      "DAY20": 0.0,
      "DAY21": 0.0,
      "DAY22": 0.0,
      "DAY23": 0.0,
      "DAY24": 0.0,
      "DAY25": 0.0,
      "DAY26": 0.0,
      "DAY27": 0.0,
      "DAY28": 0.0,
      "DAY29": 0.0,
      "DAY30": 0.0,
      "DAY31": 0.0,
      "VORNR": "",
      "UVORN": "",
      "BEDID": "000000000000",
      "KAPAR": "",
      "ARBPL": "",
      "POSID": "",
      "ZZ_PSPTXT": "",
      "ZZ_NPKTXT": "",
      "ZZ_NPVTXT": "",
      "ZZCONTPERS": "",
      "ZZSUBTYPE": "",
      "ZZOBJNR": "",
      "ZZBUKRS": "",
      "ZZ_PROJN": "00000000",
      "ZZRESET_APPR": "00",
      "ZZ_INTERNAL_MEMO": "",
      "ZCPR_GUID": "001E0B8EAF221EE292EE190B74963F4A",
      "ZCPR_EXTID": "I2M_2013_M_SOFTWARE_ENG",
      "ZCPR_OBJGUID": "001E0B8EAF221EE292EE190B749A7F4A",
      "ZCPR_OBJGEXTID": "00000000000000617288",
      "ZCPR_OBJTYPE": "TTO",
      "ZZCATSSHORTT": "",
      "ZZEXP_FLAT_RATE": "",
      "ZZMOB_ERR_FLAG": "",
      "ZZBYD": "",
      "ZZ_LOCATION": "",
      "ZZSTATUS": "00",
      "ZZGUID_ITEM": "",
      "ZZPRCTR": "",
      "ZZKOSTV": "",
      "ZZ_REL_OBJ": "",
      "ARBID": "00000000",
      "WERKS": "",
      "SPLIT": "000",
      "LTXA1": "",
      "FSTAD": "0000-00-00",
      "SSTAD": "0000-00-00",
      "FENDD": "0000-00-00",
      "SENDD": "0000-00-00",
      "KBEAREST": 0,
      "VERTL": "",
      "AUTYP": "00",
      "KALID": "",
      "RPROJ_EXT": "",
      "DISPTEXTW1": "I2M_2013_M_SOFTWARE_ENG",
      "DISPTEXTW2": "Maintenance Employee Dashboard",
      "KPER_SINGLE": "",
      "KPER_COLLECT": "",
      "CPR_GUID": "",
      "CPR_EXTID": "",
      "CPR_OBJGUID": "",
      "CPR_OBJGEXTID": "",
      "CPR_OBJTYPE": "",
      "CPR_TEXT": "",
      "CPR_OBJTEXT": "",
      "PERASCE": "00000000",
      "PRTXTCE": "",
      "TASKTYPE": "",
      "TASKLEVEL": "",
      "TASKCOMPONENT": ""
    }
  ]
}